{
    "source": "EMENTA: DIREITO PREVIDENCIÁRIO. PEDIDO DE REVISÃO DA RMI COM BASE EM SENTENÇA TRABALHISTA. PEDIDO DE UNIFORMIZAÇÃO DE INTERPRETAÇÃO DE LEI FEDERAL. NÃO CUMPRIMENTO DA QUESTÃO DE ORDEM Nº 36. ALEGAÇÃO DE OFENSA, DE FORMA GENÉRICA, ÀS DECISÕES DA TNU E DO STJ. ALEGAÇÃO DE OFENSA À SÚMULA TNU 67. INEXISTÊNCIA DE SIMILITUDE FÁTICA E JURÍDICA ENTRE O ACÓRDÃO OBJURGADO E OS ACÓRDÃOS PARADIGMAS. INEXISTÊNCIA DE OFENSA ÀS DECISÕES DA TNU. QUESTÃO DE ORDEM TNU Nº 22. INCIDENTE DA PARTE AUTORA NÃO CONHECIDO.   ",
    "items": [
        {
            "selected-text": "DIREITO PREVIDENCIÁRIO",
            "start": 8,
            "end": 30,
            "type": "SUBJECT"
        },
        {
            "selected-text": "PEDIDO DE REVISÃO DA RMI COM BASE EM SENTENÇA TRABALHISTA",
            "start": 32,
            "end": 89,
            "type": "SUBJECT"
        },
        {
            "selected-text": "PEDIDO DE UNIFORMIZAÇÃO DE INTERPRETAÇÃO DE LEI FEDERAL",
            "start": 91,
            "end": 146,
            "type": "TYPE_OF_APPEAL"
        },
        {
            "selected-text": "NÃO CUMPRIMENTO DA QUESTÃO DE ORDEM Nº 36",
            "start": 148,
            "end": 189,
            "type": "RATIO_DECIDENDI"
        },
        {
            "selected-text": "ALEGAÇÃO DE OFENSA, DE FORMA GENÉRICA, ÀS DECISÕES DA TNU E DO STJ",
            "start": 191,
            "end": 257,
            "type": "RATIO_DECIDENDI"
        },
        {
            "selected-text": "ALEGAÇÃO DE OFENSA À SÚMULA TNU 67",
            "start": 259,
            "end": 293,
            "type": "RATIO_DECIDENDI"
        },
        {
            "selected-text": "INEXISTÊNCIA DE SIMILITUDE FÁTICA E JURÍDICA ENTRE O ACÓRDÃO OBJURGADO E OS ACÓRDÃOS PARADIGMAS",
            "start": 295,
            "end": 390,
            "type": "RATIO_DECIDENDI"
        },
        {
            "selected-text": "INEXISTÊNCIA DE OFENSA ÀS DECISÕES DA TNU",
            "start": 392,
            "end": 433,
            "type": "RATIO_DECIDENDI"
        },
        {
            "selected-text": "QUESTÃO DE ORDEM TNU Nº 22",
            "start": 435,
            "end": 461,
            "type": "RATIO_DECIDENDI"
        },
        {
            "selected-text": "INCIDENTE DA PARTE AUTORA NÃO CONHECIDO",
            "start": 463,
            "end": 502,
            "type": "NOT_HEARD"
        }
    ]
}